transipddnsclient/__init__.py
transipddnsclient/__main__.py
transipddnsclient/core.py
transipddnsclient/externalip.py
transipddnsclient/transip.py
transipddnsclient/utils.py
transipddnsclient-1.1.0.dist-info/LICENSE
transipddnsclient-1.1.0.dist-info/METADATA
transipddnsclient-1.1.0.dist-info/WHEEL
transipddnsclient-1.1.0.dist-info/top_level.txt
transipddnsclient-1.1.0.dist-info/RECORD
