Metadata-Version: 2.1
Name: transipddnsclient
Version: 1.1.0
Summary: TransIP dDNS Client
Home-page: https://github.com/kvdheijden/transip-ddns-client
Author: kvdheijden
Author-email: koen@kvdheijden.com
License: MIT
Project-URL: Documentation, https://github.com/kvdheijden/transip-ddns-client/wiki
Project-URL: Source, https://github.com/kvdheijden/transip-ddns-client
Project-URL: Tracker, https://github.com/kvdheijden/transip-ddns-client/issues
Keywords: dynamic dns transip ddns
Platform: UNKNOWN
Classifier: Development Status :: 4 - Beta
Classifier: License :: OSI Approved :: MIT License
Classifier: Programming Language :: Python :: 3.7
Requires-Python: >=3.7
Requires-Dist: requests (~=2.25.1)
Requires-Dist: pyOpenSSL (~=20.0.1)
Requires-Dist: netifaces (~=0.11.0)
